tcpnetlock/__init__.py
tcpnetlock/common.py
tcpnetlock/constants.py
tcpnetlock/protocol.py
tcpnetlock/cli/__init__.py
tcpnetlock/cli/common.py
tcpnetlock/cli/tnl_client.py
tcpnetlock/cli/tnl_do.py
tcpnetlock/cli/tnl_server.py
tcpnetlock/client/__init__.py
tcpnetlock/client/action.py
tcpnetlock/client/client.py
tcpnetlock/server/__init__.py
tcpnetlock/server/action.py
tcpnetlock/server/action_handlers.py
tcpnetlock/server/background_thread.py
tcpnetlock/server/context.py
tcpnetlock/server/lock.py
tcpnetlock/server/server.py
tcpnetlock-0.1.8.dist-info/METADATA
tcpnetlock-0.1.8.dist-info/RECORD
tcpnetlock-0.1.8.dist-info/WHEEL
tcpnetlock-0.1.8.dist-info/entry_points.txt
tcpnetlock-0.1.8.dist-info/top_level.txt
